[{"indicator":"SE.ADT.1524.LT.FM.ZS","name":"Literacy rate, youth (ages 15-24), gender parity index (GPI)","topics":["Education ","Gender","Social Development "]},{"indicator":"SE.ENR.PRIM.FM.ZS","name":"School enrollment, primary (gross), gender parity index (GPI)","topics":["Education ","Gender","Social Development "]},{"indicator":"SE.ENR.SECO.FM.ZS","name":"School enrollment, secondary (gross), gender parity index (GPI)","topics":["Education ","Gender","Social Development "]},{"indicator":"SE.ENR.TERT.FM.ZS","name":"School enrollment, tertiary (gross), gender parity index (GPI)","topics":["Education ","Gender","Social Development "]}]